{"slug": "1-paid-app-in-the-us-apple-app-store-on-january-30", "last_updated": 1769384477.901192, "uptime_str": "0:00:00", "message_rate": 1.1388392609865314, "price": {"bid": 0.001, "ask": 0.999, "mid": 0.5, "spread_pct": 99.8998998998999}, "stats": {"aggression_buy": 0, "aggression_sell": 0, "max_impact_ticks": 0, "max_impact_pct": 0}, "windows": {"5m": {"trades": 0, "volume_proxy": 0, "avg_spread": 99.8998998998999}, "1h": {"trades": 0, "volume_proxy": 0, "avg_spread": 99.8998998998999}, "24h": {"trades": 0, "volume_proxy": 0, "avg_spread": 99.8998998998999}, "all": {"trades": 0, "volume_proxy": 0, "avg_spread": 99.8998998998999}}, "distributions": {"spread": {"5": 99.8998998998999, "25": 99.8998998998999, "50": 99.8998998998999, "75": 99.8998998998999, "95": 99.8998998998999, "max": 99.8998998998999, "min": 99.8998998998999}, "impact": {"5": 0, "25": 0, "50": 0, "75": 0, "95": 0, "max": 0, "min": 0}}, "last_alert": null, "raw_history": [[1769384477.901192, "spread", 99.8998998998999]], "start_time_epoch": 1769384477.023105}